{"nodes": [{"id": "workspaces_did_you_know_tests_test_schema_migrations_py", "label": "test_schema_migrations.py", "file_type": "code", "source_file": "tests/test_schema_migrations.py", "source_location": "L1"}, {"id": "tests_test_schema_migrations_testschemamigrations", "label": "TestSchemaMigrations", "file_type": "code", "source_file": "tests/test_schema_migrations.py", "source_location": "L14"}, {"id": "tests_test_schema_migrations_testschemamigrations_test_db_connection", "label": ".test_db_connection()", "file_type": "code", "source_file": "tests/test_schema_migrations.py", "source_location": "L18"}, {"id": "tests_test_schema_migrations_testschemamigrations_clean_db", "label": ".clean_db()", "file_type": "code", "source_file": "tests/test_schema_migrations.py", "source_location": "L32"}, {"id": "tests_test_schema_migrations_testschemamigrations_test_full_migration_sequence", "label": ".test_full_migration_sequence()", "file_type": "code", "source_file": "tests/test_schema_migrations.py", "source_location": "L69"}, {"id": "tests_test_schema_migrations_testschemamigrations_test_verify_tables_and_indexes", "label": ".test_verify_tables_and_indexes()", "file_type": "code", "source_file": "tests/test_schema_migrations.py", "source_location": "L99"}, {"id": "tests_test_schema_migrations_testschemamigrations_test_verify_check_constraints", "label": ".test_verify_check_constraints()", "file_type": "code", "source_file": "tests/test_schema_migrations.py", "source_location": "L161"}, {"id": "tests_test_schema_migrations_testschemamigrations_test_updated_at_triggers", "label": ".test_updated_at_triggers()", "file_type": "code", "source_file": "tests/test_schema_migrations.py", "source_location": "L219"}, {"id": "tests_test_schema_migrations_testschemamigrations_test_idempotency", "label": ".test_idempotency()", "file_type": "code", "source_file": "tests/test_schema_migrations.py", "source_location": "L286"}, {"id": "tests_test_schema_migrations_rationale_1", "label": "Integration tests for the actual schema migrations.", "file_type": "rationale", "source_file": "tests/test_schema_migrations.py", "source_location": "L1"}, {"id": "tests_test_schema_migrations_rationale_15", "label": "Integration tests for the actual schema migrations.", "file_type": "rationale", "source_file": "tests/test_schema_migrations.py", "source_location": "L15"}, {"id": "tests_test_schema_migrations_rationale_19", "label": "Create a test database connection.", "file_type": "rationale", "source_file": "tests/test_schema_migrations.py", "source_location": "L19"}, {"id": "tests_test_schema_migrations_rationale_33", "label": "Clean the database before each test.", "file_type": "rationale", "source_file": "tests/test_schema_migrations.py", "source_location": "L33"}, {"id": "tests_test_schema_migrations_rationale_70", "label": "Test applying all 4 migrations in sequence.", "file_type": "rationale", "source_file": "tests/test_schema_migrations.py", "source_location": "L70"}, {"id": "tests_test_schema_migrations_rationale_100", "label": "Verify all tables, indexes, and constraints are created correctly.", "file_type": "rationale", "source_file": "tests/test_schema_migrations.py", "source_location": "L100"}, {"id": "tests_test_schema_migrations_rationale_162", "label": "Verify CHECK constraints on status columns.", "file_type": "rationale", "source_file": "tests/test_schema_migrations.py", "source_location": "L162"}, {"id": "tests_test_schema_migrations_rationale_220", "label": "Verify updated_at triggers work correctly.", "file_type": "rationale", "source_file": "tests/test_schema_migrations.py", "source_location": "L220"}, {"id": "tests_test_schema_migrations_rationale_287", "label": "Test that migrations can be run multiple times without issues.", "file_type": "rationale", "source_file": "tests/test_schema_migrations.py", "source_location": "L287"}], "edges": [{"source": "workspaces_did_you_know_tests_test_schema_migrations_py", "target": "asyncio", "relation": "imports", "context": "import", "confidence": "EXTRACTED", "source_file": "tests/test_schema_migrations.py", "source_location": "L2", "weight": 1.0}, {"source": "workspaces_did_you_know_tests_test_schema_migrations_py", "target": "asyncpg", "relation": "imports", "context": "import", "confidence": "EXTRACTED", "source_file": "tests/test_schema_migrations.py", "source_location": "L3", "weight": 1.0}, {"source": "workspaces_did_you_know_tests_test_schema_migrations_py", "target": "os", "relation": "imports", "context": "import", "confidence": "EXTRACTED", "source_file": "tests/test_schema_migrations.py", "source_location": "L4", "weight": 1.0}, {"source": "workspaces_did_you_know_tests_test_schema_migrations_py", "target": "pytest", "relation": "imports", "context": "import", "confidence": "EXTRACTED", "source_file": "tests/test_schema_migrations.py", "source_location": "L5", "weight": 1.0}, {"source": "workspaces_did_you_know_tests_test_schema_migrations_py", "target": "sys", "relation": "imports", "context": "import", "confidence": "EXTRACTED", "source_file": "tests/test_schema_migrations.py", "source_location": "L6", "weight": 1.0}, {"source": "workspaces_did_you_know_tests_test_schema_migrations_py", "target": "pathlib", "relation": "imports_from", "context": "import", "confidence": "EXTRACTED", "source_file": "tests/test_schema_migrations.py", "source_location": "L7", "weight": 1.0}, {"source": "workspaces_did_you_know_tests_test_schema_migrations_py", "target": "shared_migrate", "relation": "imports_from", "context": "import", "confidence": "EXTRACTED", "source_file": "tests/test_schema_migrations.py", "source_location": "L10", "weight": 1.0}, {"source": "workspaces_did_you_know_tests_test_schema_migrations_py", "target": "tests_test_schema_migrations_testschemamigrations", "relation": "contains", "confidence": "EXTRACTED", "source_file": "tests/test_schema_migrations.py", "source_location": "L14", "weight": 1.0}, {"source": "tests_test_schema_migrations_testschemamigrations", "target": "tests_test_schema_migrations_testschemamigrations_test_db_connection", "relation": "method", "confidence": "EXTRACTED", "source_file": "tests/test_schema_migrations.py", "source_location": "L18", "weight": 1.0}, {"source": "tests_test_schema_migrations_testschemamigrations", "target": "tests_test_schema_migrations_testschemamigrations_clean_db", "relation": "method", "confidence": "EXTRACTED", "source_file": "tests/test_schema_migrations.py", "source_location": "L32", "weight": 1.0}, {"source": "tests_test_schema_migrations_testschemamigrations", "target": "tests_test_schema_migrations_testschemamigrations_test_full_migration_sequence", "relation": "method", "confidence": "EXTRACTED", "source_file": "tests/test_schema_migrations.py", "source_location": "L69", "weight": 1.0}, {"source": "tests_test_schema_migrations_testschemamigrations", "target": "tests_test_schema_migrations_testschemamigrations_test_verify_tables_and_indexes", "relation": "method", "confidence": "EXTRACTED", "source_file": "tests/test_schema_migrations.py", "source_location": "L99", "weight": 1.0}, {"source": "tests_test_schema_migrations_testschemamigrations", "target": "tests_test_schema_migrations_testschemamigrations_test_verify_check_constraints", "relation": "method", "confidence": "EXTRACTED", "source_file": "tests/test_schema_migrations.py", "source_location": "L161", "weight": 1.0}, {"source": "tests_test_schema_migrations_testschemamigrations", "target": "tests_test_schema_migrations_testschemamigrations_test_updated_at_triggers", "relation": "method", "confidence": "EXTRACTED", "source_file": "tests/test_schema_migrations.py", "source_location": "L219", "weight": 1.0}, {"source": "tests_test_schema_migrations_testschemamigrations", "target": "tests_test_schema_migrations_testschemamigrations_test_idempotency", "relation": "method", "confidence": "EXTRACTED", "source_file": "tests/test_schema_migrations.py", "source_location": "L286", "weight": 1.0}, {"source": "tests_test_schema_migrations_rationale_1", "target": "workspaces_did_you_know_tests_test_schema_migrations_py", "relation": "rationale_for", "confidence": "EXTRACTED", "source_file": "tests/test_schema_migrations.py", "source_location": "L1", "weight": 1.0}, {"source": "tests_test_schema_migrations_rationale_15", "target": "tests_test_schema_migrations_testschemamigrations", "relation": "rationale_for", "confidence": "EXTRACTED", "source_file": "tests/test_schema_migrations.py", "source_location": "L15", "weight": 1.0}, {"source": "tests_test_schema_migrations_rationale_19", "target": "tests_test_schema_migrations_testschemamigrations_test_db_connection", "relation": "rationale_for", "confidence": "EXTRACTED", "source_file": "tests/test_schema_migrations.py", "source_location": "L19", "weight": 1.0}, {"source": "tests_test_schema_migrations_rationale_33", "target": "tests_test_schema_migrations_testschemamigrations_clean_db", "relation": "rationale_for", "confidence": "EXTRACTED", "source_file": "tests/test_schema_migrations.py", "source_location": "L33", "weight": 1.0}, {"source": "tests_test_schema_migrations_rationale_70", "target": "tests_test_schema_migrations_testschemamigrations_test_full_migration_sequence", "relation": "rationale_for", "confidence": "EXTRACTED", "source_file": "tests/test_schema_migrations.py", "source_location": "L70", "weight": 1.0}, {"source": "tests_test_schema_migrations_rationale_100", "target": "tests_test_schema_migrations_testschemamigrations_test_verify_tables_and_indexes", "relation": "rationale_for", "confidence": "EXTRACTED", "source_file": "tests/test_schema_migrations.py", "source_location": "L100", "weight": 1.0}, {"source": "tests_test_schema_migrations_rationale_162", "target": "tests_test_schema_migrations_testschemamigrations_test_verify_check_constraints", "relation": "rationale_for", "confidence": "EXTRACTED", "source_file": "tests/test_schema_migrations.py", "source_location": "L162", "weight": 1.0}, {"source": "tests_test_schema_migrations_rationale_220", "target": "tests_test_schema_migrations_testschemamigrations_test_updated_at_triggers", "relation": "rationale_for", "confidence": "EXTRACTED", "source_file": "tests/test_schema_migrations.py", "source_location": "L220", "weight": 1.0}, {"source": "tests_test_schema_migrations_rationale_287", "target": "tests_test_schema_migrations_testschemamigrations_test_idempotency", "relation": "rationale_for", "confidence": "EXTRACTED", "source_file": "tests/test_schema_migrations.py", "source_location": "L287", "weight": 1.0}], "raw_calls": [{"caller_nid": "tests_test_schema_migrations_testschemamigrations_test_db_connection", "callee": "getenv", "is_member_call": true, "source_file": "/workspaces/did-you-know/tests/test_schema_migrations.py", "source_location": "L20", "receiver": null}, {"caller_nid": "tests_test_schema_migrations_testschemamigrations_test_db_connection", "callee": "skip", "is_member_call": true, "source_file": "/workspaces/did-you-know/tests/test_schema_migrations.py", "source_location": "L22", "receiver": null}, {"caller_nid": "tests_test_schema_migrations_testschemamigrations_test_db_connection", "callee": "connect", "is_member_call": true, "source_file": "/workspaces/did-you-know/tests/test_schema_migrations.py", "source_location": "L25", "receiver": null}, {"caller_nid": "tests_test_schema_migrations_testschemamigrations_test_db_connection", "callee": "close", "is_member_call": true, "source_file": "/workspaces/did-you-know/tests/test_schema_migrations.py", "source_location": "L27", "receiver": null}, {"caller_nid": "tests_test_schema_migrations_testschemamigrations_test_db_connection", "callee": "skip", "is_member_call": true, "source_file": "/workspaces/did-you-know/tests/test_schema_migrations.py", "source_location": "L29", "receiver": null}, {"caller_nid": "tests_test_schema_migrations_testschemamigrations_clean_db", "callee": "fetch", "is_member_call": true, "source_file": "/workspaces/did-you-know/tests/test_schema_migrations.py", "source_location": "L37", "receiver": null}, {"caller_nid": "tests_test_schema_migrations_testschemamigrations_clean_db", "callee": "execute", "is_member_call": true, "source_file": "/workspaces/did-you-know/tests/test_schema_migrations.py", "source_location": "L48", "receiver": null}, {"caller_nid": "tests_test_schema_migrations_testschemamigrations_clean_db", "callee": "fetch", "is_member_call": true, "source_file": "/workspaces/did-you-know/tests/test_schema_migrations.py", "source_location": "L51", "receiver": null}, {"caller_nid": "tests_test_schema_migrations_testschemamigrations_clean_db", "callee": "execute", "is_member_call": true, "source_file": "/workspaces/did-you-know/tests/test_schema_migrations.py", "source_location": "L61", "receiver": null}, {"caller_nid": "tests_test_schema_migrations_testschemamigrations_clean_db", "callee": "execute", "is_member_call": true, "source_file": "/workspaces/did-you-know/tests/test_schema_migrations.py", "source_location": "L64", "receiver": null}, {"caller_nid": "tests_test_schema_migrations_testschemamigrations_test_full_migration_sequence", "callee": "getenv", "is_member_call": true, "source_file": "/workspaces/did-you-know/tests/test_schema_migrations.py", "source_location": "L71", "receiver": null}, {"caller_nid": "tests_test_schema_migrations_testschemamigrations_test_full_migration_sequence", "callee": "skip", "is_member_call": true, "source_file": "/workspaces/did-you-know/tests/test_schema_migrations.py", "source_location": "L73", "receiver": null}, {"caller_nid": "tests_test_schema_migrations_testschemamigrations_test_full_migration_sequence", "callee": "Path", "is_member_call": false, "source_file": "/workspaces/did-you-know/tests/test_schema_migrations.py", "source_location": "L76", "receiver": null}, {"caller_nid": "tests_test_schema_migrations_testschemamigrations_test_full_migration_sequence", "callee": "run_migrations", "is_member_call": false, "source_file": "/workspaces/did-you-know/tests/test_schema_migrations.py", "source_location": "L77", "receiver": null}, {"caller_nid": "tests_test_schema_migrations_testschemamigrations_test_full_migration_sequence", "callee": "fetch", "is_member_call": true, "source_file": "/workspaces/did-you-know/tests/test_schema_migrations.py", "source_location": "L87", "receiver": null}, {"caller_nid": "tests_test_schema_migrations_testschemamigrations_test_verify_tables_and_indexes", "callee": "getenv", "is_member_call": true, "source_file": "/workspaces/did-you-know/tests/test_schema_migrations.py", "source_location": "L101", "receiver": null}, {"caller_nid": "tests_test_schema_migrations_testschemamigrations_test_verify_tables_and_indexes", "callee": "skip", "is_member_call": true, "source_file": "/workspaces/did-you-know/tests/test_schema_migrations.py", "source_location": "L103", "receiver": null}, {"caller_nid": "tests_test_schema_migrations_testschemamigrations_test_verify_tables_and_indexes", "callee": "Path", "is_member_call": false, "source_file": "/workspaces/did-you-know/tests/test_schema_migrations.py", "source_location": "L106", "receiver": null}, {"caller_nid": "tests_test_schema_migrations_testschemamigrations_test_verify_tables_and_indexes", "callee": "run_migrations", "is_member_call": false, "source_file": "/workspaces/did-you-know/tests/test_schema_migrations.py", "source_location": "L107", "receiver": null}, {"caller_nid": "tests_test_schema_migrations_testschemamigrations_test_verify_tables_and_indexes", "callee": "fetch", "is_member_call": true, "source_file": "/workspaces/did-you-know/tests/test_schema_migrations.py", "source_location": "L112", "receiver": null}, {"caller_nid": "tests_test_schema_migrations_testschemamigrations_test_verify_tables_and_indexes", "callee": "fetch", "is_member_call": true, "source_file": "/workspaces/did-you-know/tests/test_schema_migrations.py", "source_location": "L122", "receiver": null}, {"caller_nid": "tests_test_schema_migrations_testschemamigrations_test_verify_tables_and_indexes", "callee": "fetch", "is_member_call": true, "source_file": "/workspaces/did-you-know/tests/test_schema_migrations.py", "source_location": "L138", "receiver": null}, {"caller_nid": "tests_test_schema_migrations_testschemamigrations_test_verify_check_constraints", "callee": "getenv", "is_member_call": true, "source_file": "/workspaces/did-you-know/tests/test_schema_migrations.py", "source_location": "L163", "receiver": null}, {"caller_nid": "tests_test_schema_migrations_testschemamigrations_test_verify_check_constraints", "callee": "skip", "is_member_call": true, "source_file": "/workspaces/did-you-know/tests/test_schema_migrations.py", "source_location": "L165", "receiver": null}, {"caller_nid": "tests_test_schema_migrations_testschemamigrations_test_verify_check_constraints", "callee": "Path", "is_member_call": false, "source_file": "/workspaces/did-you-know/tests/test_schema_migrations.py", "source_location": "L168", "receiver": null}, {"caller_nid": "tests_test_schema_migrations_testschemamigrations_test_verify_check_constraints", "callee": "run_migrations", "is_member_call": false, "source_file": "/workspaces/did-you-know/tests/test_schema_migrations.py", "source_location": "L169", "receiver": null}, {"caller_nid": "tests_test_schema_migrations_testschemamigrations_test_verify_check_constraints", "callee": "execute", "is_member_call": true, "source_file": "/workspaces/did-you-know/tests/test_schema_migrations.py", "source_location": "L175", "receiver": null}, {"caller_nid": "tests_test_schema_migrations_testschemamigrations_test_verify_check_constraints", "callee": "execute", "is_member_call": true, "source_file": "/workspaces/did-you-know/tests/test_schema_migrations.py", "source_location": "L180", "receiver": null}, {"caller_nid": "tests_test_schema_migrations_testschemamigrations_test_verify_check_constraints", "callee": "raises", "is_member_call": true, "source_file": "/workspaces/did-you-know/tests/test_schema_migrations.py", "source_location": "L186", "receiver": null}, {"caller_nid": "tests_test_schema_migrations_testschemamigrations_test_verify_check_constraints", "callee": "execute", "is_member_call": true, "source_file": "/workspaces/did-you-know/tests/test_schema_migrations.py", "source_location": "L187", "receiver": null}, {"caller_nid": "tests_test_schema_migrations_testschemamigrations_test_verify_check_constraints", "callee": "fetchval", "is_member_call": true, "source_file": "/workspaces/did-you-know/tests/test_schema_migrations.py", "source_location": "L194", "receiver": null}, {"caller_nid": "tests_test_schema_migrations_testschemamigrations_test_verify_check_constraints", "callee": "execute", "is_member_call": true, "source_file": "/workspaces/did-you-know/tests/test_schema_migrations.py", "source_location": "L201", "receiver": null}, {"caller_nid": "tests_test_schema_migrations_testschemamigrations_test_verify_check_constraints", "callee": "execute", "is_member_call": true, "source_file": "/workspaces/did-you-know/tests/test_schema_migrations.py", "source_location": "L206", "receiver": null}, {"caller_nid": "tests_test_schema_migrations_testschemamigrations_test_verify_check_constraints", "callee": "raises", "is_member_call": true, "source_file": "/workspaces/did-you-know/tests/test_schema_migrations.py", "source_location": "L212", "receiver": null}, {"caller_nid": "tests_test_schema_migrations_testschemamigrations_test_verify_check_constraints", "callee": "execute", "is_member_call": true, "source_file": "/workspaces/did-you-know/tests/test_schema_migrations.py", "source_location": "L213", "receiver": null}, {"caller_nid": "tests_test_schema_migrations_testschemamigrations_test_updated_at_triggers", "callee": "getenv", "is_member_call": true, "source_file": "/workspaces/did-you-know/tests/test_schema_migrations.py", "source_location": "L221", "receiver": null}, {"caller_nid": "tests_test_schema_migrations_testschemamigrations_test_updated_at_triggers", "callee": "skip", "is_member_call": true, "source_file": "/workspaces/did-you-know/tests/test_schema_migrations.py", "source_location": "L223", "receiver": null}, {"caller_nid": "tests_test_schema_migrations_testschemamigrations_test_updated_at_triggers", "callee": "Path", "is_member_call": false, "source_file": "/workspaces/did-you-know/tests/test_schema_migrations.py", "source_location": "L226", "receiver": null}, {"caller_nid": "tests_test_schema_migrations_testschemamigrations_test_updated_at_triggers", "callee": "run_migrations", "is_member_call": false, "source_file": "/workspaces/did-you-know/tests/test_schema_migrations.py", "source_location": "L227", "receiver": null}, {"caller_nid": "tests_test_schema_migrations_testschemamigrations_test_updated_at_triggers", "callee": "fetchval", "is_member_call": true, "source_file": "/workspaces/did-you-know/tests/test_schema_migrations.py", "source_location": "L232", "receiver": null}, {"caller_nid": "tests_test_schema_migrations_testschemamigrations_test_updated_at_triggers", "callee": "fetchrow", "is_member_call": true, "source_file": "/workspaces/did-you-know/tests/test_schema_migrations.py", "source_location": "L239", "receiver": null}, {"caller_nid": "tests_test_schema_migrations_testschemamigrations_test_updated_at_triggers", "callee": "sleep", "is_member_call": true, "source_file": "/workspaces/did-you-know/tests/test_schema_migrations.py", "source_location": "L246", "receiver": null}, {"caller_nid": "tests_test_schema_migrations_testschemamigrations_test_updated_at_triggers", "callee": "execute", "is_member_call": true, "source_file": "/workspaces/did-you-know/tests/test_schema_migrations.py", "source_location": "L247", "receiver": null}, {"caller_nid": "tests_test_schema_migrations_testschemamigrations_test_updated_at_triggers", "callee": "fetchrow", "is_member_call": true, "source_file": "/workspaces/did-you-know/tests/test_schema_migrations.py", "source_location": "L252", "receiver": null}, {"caller_nid": "tests_test_schema_migrations_testschemamigrations_test_updated_at_triggers", "callee": "fetchval", "is_member_call": true, "source_file": "/workspaces/did-you-know/tests/test_schema_migrations.py", "source_location": "L259", "receiver": null}, {"caller_nid": "tests_test_schema_migrations_testschemamigrations_test_updated_at_triggers", "callee": "fetchrow", "is_member_call": true, "source_file": "/workspaces/did-you-know/tests/test_schema_migrations.py", "source_location": "L266", "receiver": null}, {"caller_nid": "tests_test_schema_migrations_testschemamigrations_test_updated_at_triggers", "callee": "sleep", "is_member_call": true, "source_file": "/workspaces/did-you-know/tests/test_schema_migrations.py", "source_location": "L273", "receiver": null}, {"caller_nid": "tests_test_schema_migrations_testschemamigrations_test_updated_at_triggers", "callee": "execute", "is_member_call": true, "source_file": "/workspaces/did-you-know/tests/test_schema_migrations.py", "source_location": "L274", "receiver": null}, {"caller_nid": "tests_test_schema_migrations_testschemamigrations_test_updated_at_triggers", "callee": "fetchrow", "is_member_call": true, "source_file": "/workspaces/did-you-know/tests/test_schema_migrations.py", "source_location": "L279", "receiver": null}, {"caller_nid": "tests_test_schema_migrations_testschemamigrations_test_idempotency", "callee": "getenv", "is_member_call": true, "source_file": "/workspaces/did-you-know/tests/test_schema_migrations.py", "source_location": "L288", "receiver": null}, {"caller_nid": "tests_test_schema_migrations_testschemamigrations_test_idempotency", "callee": "skip", "is_member_call": true, "source_file": "/workspaces/did-you-know/tests/test_schema_migrations.py", "source_location": "L290", "receiver": null}, {"caller_nid": "tests_test_schema_migrations_testschemamigrations_test_idempotency", "callee": "Path", "is_member_call": false, "source_file": "/workspaces/did-you-know/tests/test_schema_migrations.py", "source_location": "L292", "receiver": null}, {"caller_nid": "tests_test_schema_migrations_testschemamigrations_test_idempotency", "callee": "run_migrations", "is_member_call": false, "source_file": "/workspaces/did-you-know/tests/test_schema_migrations.py", "source_location": "L295", "receiver": null}, {"caller_nid": "tests_test_schema_migrations_testschemamigrations_test_idempotency", "callee": "run_migrations", "is_member_call": false, "source_file": "/workspaces/did-you-know/tests/test_schema_migrations.py", "source_location": "L299", "receiver": null}, {"caller_nid": "tests_test_schema_migrations_testschemamigrations_test_idempotency", "callee": "run_migrations", "is_member_call": false, "source_file": "/workspaces/did-you-know/tests/test_schema_migrations.py", "source_location": "L303", "receiver": null}]}